Metadata-Version: 1.0
Name: py2d-fixed
Version: 0.1
Summary: Py2D library of 2D-game-related algorithms
Home-page: http://www.github.com/sseemayer/py2d
Author: Stefan Seemayer
Author-email: mail@semicolonsoftware.de
License: UNKNOWN
Platform: UNKNOWN
